event/__init__.py
event/sports/__init__.py
event/sports/main_class.py
event/sports/soccer/__init__.py
event/sports/soccer/application/HPUS.py
event/sports/soccer/application/__init__.py
event/sports/soccer/application/heatmap.py
event/sports/soccer/application/poss_util.py
event/sports/soccer/application/result_sim.py
event/sports/soccer/dataloaders/UEID_loader.py
event/sports/soccer/dataloaders/__init__.py
event/sports/soccer/examples/example.py
event/sports/soccer/inference/FMS_inference.py
event/sports/soccer/inference/LEM_inference.py
event/sports/soccer/inference/UEID_inference.py
event/sports/soccer/main_class_soccer/main.py
event/sports/soccer/models/FMS.py
event/sports/soccer/models/LEM.py
event/sports/soccer/models/LEM_action.py
event/sports/soccer/models/MAJ.py
event/sports/soccer/models/NMSTPP.py
event/sports/soccer/models/Seq2Event.py
event/sports/soccer/models/__init__.py
event/sports/soccer/trainers/FMS_train.py
event/sports/soccer/trainers/LEM_train.py
event/sports/soccer/trainers/MAJ_train.py
event/sports/soccer/trainers/UEID_train.py
event/sports/soccer/trainers/__init__.py
event/sports/soccer/utils/FMS_cost_function.py
event/sports/soccer/utils/LEM_cost_function.py
event/sports/soccer/utils/MAJ_cost_function.py
event/sports/soccer/utils/UEID_cost_function.py
event/sports/soccer/utils/UEID_preprocessing.py
event/sports/soccer/utils/__init__.py
event/sports/soccer/utils/test_f1.py
test/dataset/script/check_event_dist.py
test/dataset/script/check_interevent_time_dist.py
test/dataset/script/check_pose_len.py
test/dataset/script/class2index.py
test/dataset/script/create_dataset.py
test/dataset/script/dataset_split.py
openstarlab_event-0.1.25.dist-info/LICENSE.md
openstarlab_event-0.1.25.dist-info/METADATA
openstarlab_event-0.1.25.dist-info/WHEEL
openstarlab_event-0.1.25.dist-info/top_level.txt
openstarlab_event-0.1.25.dist-info/RECORD
