Metadata-Version: 2.1
Name: openstarlab_event
Version: 0.1.25
Summary: openstarlab event modeling package
Author-email: Calvin Yeung <yeung.chikwong@g.sp.m.is.nagoya-u.ac.jp>
License: Apache License 2.0
Project-URL: Homepage, https://github.com/open-starlab/Event
Classifier: Programming Language :: Python :: 3
Classifier: License :: OSI Approved :: Apache Software License
Classifier: Operating System :: OS Independent
Requires-Python: >=3.8
License-File: LICENSE.md
Requires-Dist: pandas>=1.3.0
Requires-Dist: numpy>=1.21.0
Requires-Dist: torchprofile
Requires-Dist: optuna
Requires-Dist: matplotlib
Requires-Dist: matplotsoccer
Requires-Dist: scipy
